{
  "sku_id": "1285465421214126100",
  "name": "M. Bison",
  "summary": "The leader of Shadaloo, who was believed to be dead. Very fond of power... the Psycho kind.",
  "store_listing_id": "1285465421222252595",
  "banner": "1285465421356732426",
  "unpublished_at": null,
  "styles": {
    "background_colors": [
      5577756,
      1118536
    ],
    "button_colors": [
      5793266,
      5793266
    ],
    "confetti_colors": [
      43772,
      15774258,
      16414587,
      3000177,
      9739511
    ]
  },
  "prices": {
    "0": {
      "country_prices": {
        "country_code": "US",
        "prices": [
          {
            "amount": 1299,
            "currency": "usd",
            "exponent": 2
          }
        ]
      }
    },
    "4": {
      "country_prices": {
        "country_code": "US",
        "prices": [
          {
            "amount": 999,
            "currency": "usd",
            "exponent": 2
          }
        ]
      }
    },
    "5": {
      "country_prices": {
        "country_code": "US",
        "prices": [
          {
            "amount": 1299,
            "currency": "usd",
            "exponent": 2
          }
        ]
      }
    },
    "7": {
      "country_prices": {
        "country_code": "US",
        "prices": [
          {
            "amount": 999,
            "currency": "usd",
            "exponent": 2
          }
        ]
      }
    }
  },
  "items": [
    {
      "type": 0,
      "id": "1285465421230637126",
      "sku_id": "1285465421214126100",
      "asset": "a_66f69effef43b4f7c4f5d0739079a947",
      "label": "The avatar dons M. Bison's signature cap while summoning menacing purple energy orbs that radiate dark power from each of his hands."
    }
  ],
  "type": 0,
  "premium_type": 0,
  "category_sku_id": "1285465421339693076",
  "google_sku_ids": {
    "5": "1285465421214126100_1287867521810305034",
    "7": "1285465421214126100_1287867532002328619"
  }
}